{"changes":[{"id":35472,"name":"Pauwel Kwak","supermarket":"dirk","category":"dranken, sap, koffie & thee","unit":"4 x 330 ml","unit_type":"ml","price_per_unit":6.053030303030303,"first_price":2.02,"first_date":"2026-03-12 11:08:51","latest_price":7.99,"latest_date":"2026-03-19 06:23:46","pct_change":295.54,"abs_change":5.97},{"id":35742,"name":"Silvo Oregano","supermarket":"dirk","category":"voorraadkast","unit":"10 g","unit_type":"g","price_per_unit":259,"first_price":0.74,"first_date":"2026-03-12 11:09:41","latest_price":2.59,"latest_date":"2026-03-19 06:24:33","pct_change":250,"abs_change":1.85},{"id":34841,"name":"Hak Witte bonen in tomatensaus","supermarket":"dirk","category":"aardappelen, groente & fruit","unit":"720 g","unit_type":"g","price_per_unit":4.152777777777778,"first_price":0.99,"first_date":"2026-03-12 11:05:19","latest_price":2.99,"latest_date":"2026-03-19 06:20:44","pct_change":202.02,"abs_change":2},{"id":34842,"name":"Hak Kapucijners","supermarket":"dirk","category":"aardappelen, groente & fruit","unit":"715 g","unit_type":"g","price_per_unit":4.125874125874126,"first_price":0.99,"first_date":"2026-03-12 11:05:19","latest_price":2.95,"latest_date":"2026-03-19 06:20:44","pct_change":197.98,"abs_change":1.96},{"id":36677,"name":"Milka Chocoladereep alpenmelk","supermarket":"dirk","category":"snacks & snoep","unit":"250 g","unit_type":"g","price_per_unit":15.960000000000003,"first_price":1.35,"first_date":"2026-03-12 11:13:04","latest_price":3.99,"latest_date":"2026-03-19 06:27:48","pct_change":195.56,"abs_change":2.64},{"id":34878,"name":"Hak Spinazie met room","supermarket":"dirk","category":"aardappelen, groente & fruit","unit":"345 g","unit_type":"g","price_per_unit":8.26086956521739,"first_price":0.99,"first_date":"2026-03-12 11:05:19","latest_price":2.85,"latest_date":"2026-03-19 06:20:44","pct_change":187.88,"abs_change":1.86},{"id":35844,"name":"Silvo Peper zwart gemalen","supermarket":"dirk","category":"voorraadkast","unit":"40 g","unit_type":"g","price_per_unit":77.25,"first_price":1.09,"first_date":"2026-03-12 11:09:41","latest_price":3.09,"latest_date":"2026-03-19 06:24:33","pct_change":183.49,"abs_change":2},{"id":34874,"name":"Hak Rode kool met stukjes appel","supermarket":"dirk","category":"aardappelen, groente & fruit","unit":"700 g","unit_type":"g","price_per_unit":3.985714285714286,"first_price":0.99,"first_date":"2026-03-12 11:05:19","latest_price":2.79,"latest_date":"2026-03-19 06:20:44","pct_change":181.82,"abs_change":1.8},{"id":34845,"name":"Hak Sperziebonen fijn gebroken","supermarket":"dirk","category":"aardappelen, groente & fruit","unit":"675 g","unit_type":"g","price_per_unit":3.9259259259259256,"first_price":0.99,"first_date":"2026-03-12 11:05:19","latest_price":2.65,"latest_date":"2026-03-19 06:20:44","pct_change":167.68,"abs_change":1.66},{"id":36520,"name":"Prodent Tandpasta menthol power","supermarket":"dirk","category":"kind & drogisterij","unit":"75 ml","unit_type":"ml","price_per_unit":34.53333333333333,"first_price":0.99,"first_date":"2026-03-12 11:12:36","latest_price":2.59,"latest_date":"2026-03-19 06:27:21","pct_change":161.62,"abs_change":1.6},{"id":34789,"name":"Hak Rode bieten sticks zoetzuur","supermarket":"dirk","category":"aardappelen, groente & fruit","unit":"355 g","unit_type":"g","price_per_unit":6.619718309859155,"first_price":0.99,"first_date":"2026-03-12 11:05:19","latest_price":2.35,"latest_date":"2026-03-19 06:20:44","pct_change":137.37,"abs_change":1.36},{"id":34843,"name":"Hak Doperwten extra fijn","supermarket":"dirk","category":"aardappelen, groente & fruit","unit":"350 g","unit_type":"g","price_per_unit":6.714285714285714,"first_price":0.99,"first_date":"2026-03-12 11:05:19","latest_price":2.35,"latest_date":"2026-03-19 06:20:44","pct_change":137.37,"abs_change":1.36},{"id":36521,"name":"Parodontax Tandpasta active repair freshmint","supermarket":"dirk","category":"kind & drogisterij","unit":"75 ml","unit_type":"ml","price_per_unit":93.2,"first_price":2.99,"first_date":"2026-03-12 11:12:36","latest_price":6.99,"latest_date":"2026-03-19 06:27:21","pct_change":133.78,"abs_change":4},{"id":34857,"name":"Hak Gesneden bonen","supermarket":"dirk","category":"aardappelen, groente & fruit","unit":"340 g","unit_type":"g","price_per_unit":6.735294117647059,"first_price":0.99,"first_date":"2026-03-12 11:05:19","latest_price":2.29,"latest_date":"2026-03-19 06:20:44","pct_change":131.31,"abs_change":1.3},{"id":34876,"name":"Hak Rode kool met stukjes peer en kaneel","supermarket":"dirk","category":"aardappelen, groente & fruit","unit":"355 g","unit_type":"g","price_per_unit":6.450704225352113,"first_price":0.99,"first_date":"2026-03-12 11:05:19","latest_price":2.29,"latest_date":"2026-03-19 06:20:44","pct_change":131.31,"abs_change":1.3},{"id":36635,"name":"Lay's Ribbelchips max apple & caramel","supermarket":"dirk","category":"snacks & snoep","unit":"185 g","unit_type":"g","price_per_unit":12.162162162162163,"first_price":0.99,"first_date":"2026-03-12 11:12:50","latest_price":2.25,"latest_date":"2026-03-19 06:27:35","pct_change":127.27,"abs_change":1.26},{"id":34635,"name":"Hak Appelmoes met een vleugje kaneel","supermarket":"dirk","category":"aardappelen, groente & fruit","unit":"360 g","unit_type":"g","price_per_unit":6.083333333333333,"first_price":0.99,"first_date":"2026-03-12 11:04:53","latest_price":2.19,"latest_date":"2026-03-19 06:20:22","pct_change":121.21,"abs_change":1.2},{"id":35415,"name":"Grolsch Pilsener alcoholvrij 6x33 cl","supermarket":"dirk","category":"dranken, sap, koffie & thee","unit":"1,98 liter","unit_type":"ml","price_per_unit":2.6717171717171717,"first_price":2.49,"first_date":"2026-03-12 11:08:51","latest_price":5.29,"latest_date":"2026-03-19 06:23:46","pct_change":112.45,"abs_change":2.8},{"id":35425,"name":"Hertog Jan Pilsener alcoholvrij 24 x 30cl","supermarket":"dirk","category":"dranken, sap, koffie & thee","unit":"7,2 liter","unit_type":"ml","price_per_unit":2.6374999999999997,"first_price":8.99,"first_date":"2026-03-12 11:08:51","latest_price":18.99,"latest_date":"2026-03-19 06:23:46","pct_change":111.23,"abs_change":10},{"id":35426,"name":"La Chouffe 0.0% 4x33 cl","supermarket":"dirk","category":"dranken, sap, koffie & thee","unit":"1,32 liter","unit_type":"ml","price_per_unit":5.977272727272727,"first_price":3.79,"first_date":"2026-03-12 11:08:51","latest_price":7.89,"latest_date":"2026-03-19 06:23:46","pct_change":108.18,"abs_change":4.1},{"id":34637,"name":"Hak Appelmoes extra kwaliteit","supermarket":"dirk","category":"aardappelen, groente & fruit","unit":"355 g","unit_type":"g","price_per_unit":5.605633802816901,"first_price":0.99,"first_date":"2026-03-12 11:04:53","latest_price":1.99,"latest_date":"2026-03-19 06:20:22","pct_change":101.01,"abs_change":1},{"id":34638,"name":"Hak Rabarbercompote","supermarket":"dirk","category":"aardappelen, groente & fruit","unit":"360 g","unit_type":"g","price_per_unit":5.527777777777779,"first_price":0.99,"first_date":"2026-03-12 11:04:53","latest_price":1.99,"latest_date":"2026-03-19 06:20:22","pct_change":101.01,"abs_change":1},{"id":34787,"name":"Hak Rode bieten schijven","supermarket":"dirk","category":"aardappelen, groente & fruit","unit":"355 g","unit_type":"g","price_per_unit":5.605633802816901,"first_price":0.99,"first_date":"2026-03-12 11:05:19","latest_price":1.99,"latest_date":"2026-03-19 06:20:44","pct_change":101.01,"abs_change":1},{"id":34850,"name":"Hak Witte bonen","supermarket":"dirk","category":"aardappelen, groente & fruit","unit":"365 g","unit_type":"g","price_per_unit":5.4520547945205475,"first_price":0.99,"first_date":"2026-03-12 11:05:19","latest_price":1.99,"latest_date":"2026-03-19 06:20:44","pct_change":101.01,"abs_change":1},{"id":34875,"name":"Hak Rode kool","supermarket":"dirk","category":"aardappelen, groente & fruit","unit":"355 g","unit_type":"g","price_per_unit":5.605633802816901,"first_price":0.99,"first_date":"2026-03-12 11:05:19","latest_price":1.99,"latest_date":"2026-03-19 06:20:44","pct_change":101.01,"abs_change":1},{"id":35976,"name":"1 de Beste groentespread pompoen tandoori","supermarket":"dirk","category":"maaltijden, salades & tapas","unit":"175 g","unit_type":"g","price_per_unit":11.37142857142857,"first_price":0.99,"first_date":"2026-03-12 11:10:22","latest_price":1.99,"latest_date":"2026-03-19 06:25:14","pct_change":101.01,"abs_change":1},{"id":35163,"name":"Kips Vega paté","supermarket":"dirk","category":"vlees & vis","unit":"125 g","unit_type":"g","price_per_unit":19.12,"first_price":1.19,"first_date":"2026-03-12 11:06:26","latest_price":2.39,"latest_date":"2026-03-19 06:21:31","pct_change":100.84,"abs_change":1.2},{"id":35165,"name":"Kips Snijworst vega","supermarket":"dirk","category":"vlees & vis","unit":"125 g","unit_type":"g","price_per_unit":19.12,"first_price":1.19,"first_date":"2026-03-12 11:06:26","latest_price":2.39,"latest_date":"2026-03-19 06:21:31","pct_change":100.84,"abs_change":1.2},{"id":28897,"name":"Taksi Tropisch Fruit 1,5 L","supermarket":"jumbo","category":"frisdrank & sappen","unit":"1.5 L","unit_type":"ml","price_per_unit":1.3266666666666667,"first_price":1,"first_date":"2026-03-12 09:32:48","latest_price":1.99,"latest_date":"2026-03-19 06:14:07","pct_change":99,"abs_change":0.99},{"id":34690,"name":"1 de Beste Uien","supermarket":"dirk","category":"aardappelen, groente & fruit","unit":"2 kg","unit_type":"g","price_per_unit":0.645,"first_price":0.65,"first_date":"2026-03-12 11:05:10","latest_price":1.29,"latest_date":"2026-03-19 06:20:37","pct_change":98.46,"abs_change":0.64},{"id":34913,"name":"1 de Beste Doperwten en wortelen extra fijn","supermarket":"dirk","category":"aardappelen, groente & fruit","unit":"400 g","unit_type":"g","price_per_unit":2.225,"first_price":0.45,"first_date":"2026-03-12 11:05:19","latest_price":0.89,"latest_date":"2026-03-19 06:20:44","pct_change":97.78,"abs_change":0.44},{"id":34844,"name":"Hak Doperwtjes met worteltjes extra fijn","supermarket":"dirk","category":"aardappelen, groente & fruit","unit":"350 g","unit_type":"g","price_per_unit":5.571428571428571,"first_price":0.99,"first_date":"2026-03-12 11:05:19","latest_price":1.95,"latest_date":"2026-03-19 06:20:44","pct_change":96.97,"abs_change":0.96},{"id":35291,"name":"1 de Beste Margarine","supermarket":"dirk","category":"zuivel & kaas","unit":"500 g","unit_type":"g","price_per_unit":2.7,"first_price":0.69,"first_date":"2026-03-12 11:08:00","latest_price":1.35,"latest_date":"2026-03-19 06:22:58","pct_change":95.65,"abs_change":0.66},{"id":35885,"name":"Honig Kruidenmix hachee","supermarket":"dirk","category":"voorraadkast","unit":"63 g","unit_type":"g","price_per_unit":30.476190476190474,"first_price":0.99,"first_date":"2026-03-12 11:09:41","latest_price":1.92,"latest_date":"2026-03-19 06:24:33","pct_change":93.94,"abs_change":0.93},{"id":36272,"name":"Perfect Fit Kattenvoer droog senior kip","supermarket":"dirk","category":"huishoud & huisdieren","unit":"750 g","unit_type":"g","price_per_unit":7.666666666666666,"first_price":2.99,"first_date":"2026-03-12 11:12:08","latest_price":5.75,"latest_date":"2026-03-19 06:26:55","pct_change":92.31,"abs_change":2.76},{"id":35880,"name":"Honig Bakplaat mix prov.broccoli&rundervink","supermarket":"dirk","category":"voorraadkast","unit":"36 g","unit_type":"g","price_per_unit":52.5,"first_price":0.99,"first_date":"2026-03-12 11:09:41","latest_price":1.89,"latest_date":"2026-03-19 06:24:33","pct_change":90.91,"abs_change":0.9},{"id":35886,"name":"Honig Kruidenmix roerbakmie","supermarket":"dirk","category":"voorraadkast","unit":"41 g","unit_type":"g","price_per_unit":46.09756097560975,"first_price":0.99,"first_date":"2026-03-12 11:09:41","latest_price":1.89,"latest_date":"2026-03-19 06:24:33","pct_change":90.91,"abs_change":0.9},{"id":35889,"name":"Honig Bakplaat mix mex. courgette & kip","supermarket":"dirk","category":"voorraadkast","unit":"36 g","unit_type":"g","price_per_unit":52.5,"first_price":0.99,"first_date":"2026-03-12 11:09:41","latest_price":1.89,"latest_date":"2026-03-19 06:24:33","pct_change":90.91,"abs_change":0.9},{"id":35890,"name":"Honig Bakplaat mix boontjes&gehaktballetjes","supermarket":"dirk","category":"voorraadkast","unit":"36 g","unit_type":"g","price_per_unit":52.5,"first_price":0.99,"first_date":"2026-03-12 11:09:41","latest_price":1.89,"latest_date":"2026-03-19 06:24:33","pct_change":90.91,"abs_change":0.9},{"id":36271,"name":"Perfect Fit Kattenvoer droog adult zalm","supermarket":"dirk","category":"huishoud & huisdieren","unit":"750 g","unit_type":"g","price_per_unit":7.586666666666667,"first_price":2.99,"first_date":"2026-03-12 11:12:08","latest_price":5.69,"latest_date":"2026-03-19 06:26:55","pct_change":90.3,"abs_change":2.7},{"id":34856,"name":"Hak Hollandse bruine bonen","supermarket":"dirk","category":"aardappelen, groente & fruit","unit":"370 g","unit_type":"g","price_per_unit":5.054054054054054,"first_price":0.99,"first_date":"2026-03-12 11:05:19","latest_price":1.87,"latest_date":"2026-03-19 06:20:44","pct_change":88.89,"abs_change":0.88},{"id":34906,"name":"Hak Wortelen extra fijn","supermarket":"dirk","category":"aardappelen, groente & fruit","unit":"350 g","unit_type":"g","price_per_unit":5.342857142857143,"first_price":0.99,"first_date":"2026-03-12 11:05:19","latest_price":1.87,"latest_date":"2026-03-19 06:20:44","pct_change":88.89,"abs_change":0.88},{"id":35882,"name":"Honig Kruidenmix kip kerrie","supermarket":"dirk","category":"voorraadkast","unit":"59 g","unit_type":"g","price_per_unit":31.694915254237287,"first_price":0.99,"first_date":"2026-03-12 11:09:41","latest_price":1.87,"latest_date":"2026-03-19 06:24:33","pct_change":88.89,"abs_change":0.88},{"id":35883,"name":"Honig Kruidenmix tagliatelle roomsaus","supermarket":"dirk","category":"voorraadkast","unit":"62 g","unit_type":"g","price_per_unit":30.161290322580648,"first_price":0.99,"first_date":"2026-03-12 11:09:41","latest_price":1.87,"latest_date":"2026-03-19 06:24:33","pct_change":88.89,"abs_change":0.88},{"id":35884,"name":"Honig Kruidenmix chili con carne","supermarket":"dirk","category":"voorraadkast","unit":"42 g","unit_type":"g","price_per_unit":44.523809523809526,"first_price":0.99,"first_date":"2026-03-12 11:09:41","latest_price":1.87,"latest_date":"2026-03-19 06:24:33","pct_change":88.89,"abs_change":0.88},{"id":35887,"name":"Honig Kruidenmix boerenomelet","supermarket":"dirk","category":"voorraadkast","unit":"38 g","unit_type":"g","price_per_unit":49.21052631578947,"first_price":0.99,"first_date":"2026-03-12 11:09:41","latest_price":1.87,"latest_date":"2026-03-19 06:24:33","pct_change":88.89,"abs_change":0.88},{"id":35410,"name":"Affligem Blond 0.0%","supermarket":"dirk","category":"dranken, sap, koffie & thee","unit":"6 x 300 ml","unit_type":"ml","price_per_unit":4.083333333333333,"first_price":3.99,"first_date":"2026-03-12 11:08:51","latest_price":7.35,"latest_date":"2026-03-19 06:23:46","pct_change":84.21,"abs_change":3.36},{"id":35881,"name":"Honig Kruidenmix bami speciaal","supermarket":"dirk","category":"voorraadkast","unit":"37 g","unit_type":"g","price_per_unit":48.37837837837838,"first_price":0.99,"first_date":"2026-03-12 11:09:41","latest_price":1.79,"latest_date":"2026-03-19 06:24:33","pct_change":80.81,"abs_change":0.8},{"id":35888,"name":"Honig Kruidenmix nasi speciaal","supermarket":"dirk","category":"voorraadkast","unit":"38 g","unit_type":"g","price_per_unit":47.10526315789474,"first_price":0.99,"first_date":"2026-03-12 11:09:41","latest_price":1.79,"latest_date":"2026-03-19 06:24:33","pct_change":80.81,"abs_change":0.8},{"id":36270,"name":"Perfect Fit Kattenvoer droog adult kip","supermarket":"dirk","category":"huishoud & huisdieren","unit":"750 g","unit_type":"g","price_per_unit":7.133333333333333,"first_price":2.99,"first_date":"2026-03-12 11:12:08","latest_price":5.35,"latest_date":"2026-03-19 06:26:55","pct_change":78.93,"abs_change":2.36},{"id":35263,"name":"Sense Margarine original","supermarket":"dirk","category":"zuivel & kaas","unit":"575 g","unit_type":"g","price_per_unit":4.852173913043478,"first_price":1.59,"first_date":"2026-03-12 11:08:00","latest_price":2.79,"latest_date":"2026-03-19 06:22:58","pct_change":75.47,"abs_change":1.2},{"id":36113,"name":"Queens Pangasiusfilet pikant gekruid","supermarket":"dirk","category":"diepvries","unit":"250 g","unit_type":"g","price_per_unit":13.96,"first_price":1.99,"first_date":"2026-03-12 11:11:18","latest_price":3.49,"latest_date":"2026-03-19 06:26:08","pct_change":75.38,"abs_change":1.5},{"id":36104,"name":"Queens Pangalicious extra krokant","supermarket":"dirk","category":"diepvries","unit":"250 g","unit_type":"g","price_per_unit":13.8,"first_price":1.99,"first_date":"2026-03-12 11:11:18","latest_price":3.45,"latest_date":"2026-03-19 06:26:08","pct_change":73.37,"abs_change":1.46},{"id":35164,"name":"Kips Vega kleintjes smeerworst","supermarket":"dirk","category":"vlees & vis","unit":"120 g","unit_type":"g","price_per_unit":16.583333333333332,"first_price":1.19,"first_date":"2026-03-12 11:06:26","latest_price":1.99,"latest_date":"2026-03-19 06:21:31","pct_change":67.23,"abs_change":0.8},{"id":34866,"name":"1 de Beste Sperziebonen gebroken","supermarket":"dirk","category":"aardappelen, groente & fruit","unit":"680 g","unit_type":"g","price_per_unit":1.7499999999999998,"first_price":0.72,"first_date":"2026-03-12 11:05:19","latest_price":1.19,"latest_date":"2026-03-19 06:20:44","pct_change":65.28,"abs_change":0.47},{"id":36522,"name":"Parodontax Tandpasta ultra clean","supermarket":"dirk","category":"kind & drogisterij","unit":"75 ml","unit_type":"ml","price_per_unit":64.66666666666666,"first_price":2.99,"first_date":"2026-03-12 11:12:36","latest_price":4.85,"latest_date":"2026-03-19 06:27:21","pct_change":62.21,"abs_change":1.86},{"id":34618,"name":"1 de Beste Pitloze witte druiven","supermarket":"dirk","category":"aardappelen, groente & fruit","unit":"500 g","unit_type":"g","price_per_unit":4.78,"first_price":1.49,"first_date":"2026-03-12 11:04:45","latest_price":2.39,"latest_date":"2026-03-19 06:20:15","pct_change":60.4,"abs_change":0.9},{"id":36103,"name":"Queens Pangalicious knoflook kruiden","supermarket":"dirk","category":"diepvries","unit":"250 g","unit_type":"g","price_per_unit":12.76,"first_price":1.99,"first_date":"2026-03-12 11:11:18","latest_price":3.19,"latest_date":"2026-03-19 06:26:08","pct_change":60.3,"abs_change":1.2},{"id":36523,"name":"Parodontax Tandpasta fluoride","supermarket":"dirk","category":"kind & drogisterij","unit":"75 ml","unit_type":"ml","price_per_unit":63.86666666666667,"first_price":2.99,"first_date":"2026-03-12 11:12:36","latest_price":4.79,"latest_date":"2026-03-19 06:27:21","pct_change":60.2,"abs_change":1.8},{"id":36524,"name":"Parodontax Tandpasta whitening","supermarket":"dirk","category":"kind & drogisterij","unit":"75 ml","unit_type":"ml","price_per_unit":63.86666666666667,"first_price":2.99,"first_date":"2026-03-12 11:12:36","latest_price":4.79,"latest_date":"2026-03-19 06:27:21","pct_change":60.2,"abs_change":1.8},{"id":36569,"name":"Cheetos Spinners paprika","supermarket":"dirk","category":"snacks & snoep","unit":"110 g","unit_type":"g","price_per_unit":21.363636363636367,"first_price":1.49,"first_date":"2026-03-12 11:12:50","latest_price":2.35,"latest_date":"2026-03-19 06:27:34","pct_change":57.72,"abs_change":0.86},{"id":36565,"name":"Lay's Mama mia's","supermarket":"dirk","category":"snacks & snoep","unit":"125 g","unit_type":"g","price_per_unit":18.72,"first_price":1.49,"first_date":"2026-03-12 11:12:50","latest_price":2.34,"latest_date":"2026-03-19 06:27:34","pct_change":57.05,"abs_change":0.85},{"id":36568,"name":"Lay's Pomtips naturel","supermarket":"dirk","category":"snacks & snoep","unit":"125 g","unit_type":"g","price_per_unit":18.72,"first_price":1.49,"first_date":"2026-03-12 11:12:50","latest_price":2.34,"latest_date":"2026-03-19 06:27:34","pct_change":57.05,"abs_change":0.85},{"id":36479,"name":"Garnier Shampoo honinggoud","supermarket":"dirk","category":"kind & drogisterij","unit":"250 ml","unit_type":"ml","price_per_unit":17.96,"first_price":2.89,"first_date":"2026-03-12 11:12:29","latest_price":4.49,"latest_date":"2026-03-19 06:27:15","pct_change":55.36,"abs_change":1.6},{"id":36481,"name":"Garnier Cremespoeling honinggoud","supermarket":"dirk","category":"kind & drogisterij","unit":"200 ml","unit_type":"ml","price_per_unit":22.450000000000003,"first_price":2.89,"first_date":"2026-03-12 11:12:29","latest_price":4.49,"latest_date":"2026-03-19 06:27:15","pct_change":55.36,"abs_change":1.6},{"id":35260,"name":"Campina Botergoud roomboter voor bakken & braden","supermarket":"dirk","category":"zuivel & kaas","unit":"200 g","unit_type":"g","price_per_unit":19.25,"first_price":2.49,"first_date":"2026-03-12 11:08:00","latest_price":3.85,"latest_date":"2026-03-19 06:22:58","pct_change":54.62,"abs_change":1.36},{"id":36362,"name":"Sheba classics Paté zalm","supermarket":"dirk","category":"huishoud & huisdieren","unit":"85 g","unit_type":"g","price_per_unit":10.588235294117647,"first_price":0.59,"first_date":"2026-03-12 11:12:08","latest_price":0.9,"latest_date":"2026-03-19 06:26:55","pct_change":52.54,"abs_change":0.31},{"id":36358,"name":"Sheba Sauce lover zalm","supermarket":"dirk","category":"huishoud & huisdieren","unit":"85 g","unit_type":"g","price_per_unit":10.470588235294118,"first_price":0.59,"first_date":"2026-03-12 11:12:08","latest_price":0.89,"latest_date":"2026-03-19 06:26:55","pct_change":50.85,"abs_change":0.3},{"id":36361,"name":"Sheba Kattenvoer sauce lover met tonijn","supermarket":"dirk","category":"huishoud & huisdieren","unit":"85 g","unit_type":"g","price_per_unit":10.470588235294118,"first_price":0.59,"first_date":"2026-03-12 11:12:08","latest_price":0.89,"latest_date":"2026-03-19 06:26:55","pct_change":50.85,"abs_change":0.3},{"id":19806,"name":"Jumbo Courgette","supermarket":"jumbo","category":"aardappelen, groente & fruit","unit":null,"unit_type":null,"price_per_unit":null,"first_price":0.79,"first_date":"2026-03-12 09:05:21","latest_price":1.19,"latest_date":"2026-03-19 06:01:54","pct_change":50.63,"abs_change":0.4},{"id":35300,"name":"Campina Botergoud gezouten","supermarket":"dirk","category":"zuivel & kaas","unit":"250 g","unit_type":"g","price_per_unit":15,"first_price":2.49,"first_date":"2026-03-12 11:08:00","latest_price":3.75,"latest_date":"2026-03-19 06:22:58","pct_change":50.6,"abs_change":1.26},{"id":36762,"name":"Tony's Chocolonely wit","supermarket":"dirk","category":"snacks & snoep","unit":"180 g","unit_type":"g","price_per_unit":24.944444444444446,"first_price":2.99,"first_date":"2026-03-12 11:13:04","latest_price":4.49,"latest_date":"2026-03-19 06:27:49","pct_change":50.17,"abs_change":1.5},{"id":36729,"name":"Tony's Chocolonely Chocolonely melk pecan crunch karamel","supermarket":"dirk","category":"snacks & snoep","unit":"180 g","unit_type":"g","price_per_unit":24.72222222222222,"first_price":2.99,"first_date":"2026-03-12 11:13:04","latest_price":4.45,"latest_date":"2026-03-19 06:27:49","pct_change":48.83,"abs_change":1.46},{"id":35167,"name":"Stegeman Vegetarische curry","supermarket":"dirk","category":"vlees & vis","unit":"100 g","unit_type":"g","price_per_unit":24.900000000000002,"first_price":1.69,"first_date":"2026-03-12 11:06:26","latest_price":2.49,"latest_date":"2026-03-19 06:21:31","pct_change":47.34,"abs_change":0.8},{"id":36538,"name":"Cheetos Chipito kaas","supermarket":"dirk","category":"snacks & snoep","unit":"125 g","unit_type":"g","price_per_unit":17.52,"first_price":1.49,"first_date":"2026-03-12 11:12:50","latest_price":2.19,"latest_date":"2026-03-19 06:27:34","pct_change":46.98,"abs_change":0.7},{"id":36753,"name":"Tony's Chocolonely puur amandel zeezout","supermarket":"dirk","category":"snacks & snoep","unit":"180 g","unit_type":"g","price_per_unit":24.388888888888886,"first_price":2.99,"first_date":"2026-03-12 11:13:04","latest_price":4.39,"latest_date":"2026-03-19 06:27:49","pct_change":46.82,"abs_change":1.4},{"id":35301,"name":"Campina Botergoud ongezouten","supermarket":"dirk","category":"zuivel & kaas","unit":"250 g","unit_type":"g","price_per_unit":14.6,"first_price":2.49,"first_date":"2026-03-12 11:08:00","latest_price":3.65,"latest_date":"2026-03-19 06:22:58","pct_change":46.59,"abs_change":1.16},{"id":35302,"name":"Campina Botergoud grasboter ongezouten vloot","supermarket":"dirk","category":"zuivel & kaas","unit":"225 g","unit_type":"g","price_per_unit":16.22222222222222,"first_price":2.49,"first_date":"2026-03-12 11:08:00","latest_price":3.65,"latest_date":"2026-03-19 06:22:58","pct_change":46.59,"abs_change":1.16},{"id":36360,"name":"Sheba Kattenvoer alu pate kip","supermarket":"dirk","category":"huishoud & huisdieren","unit":"85 g","unit_type":"g","price_per_unit":10.117647058823529,"first_price":0.59,"first_date":"2026-03-12 11:12:08","latest_price":0.86,"latest_date":"2026-03-19 06:26:55","pct_change":45.76,"abs_change":0.27},{"id":35168,"name":"Stegeman Broodbeleg mediterraans","supermarket":"dirk","category":"vlees & vis","unit":"100 g","unit_type":"g","price_per_unit":24.5,"first_price":1.69,"first_date":"2026-03-12 11:06:26","latest_price":2.45,"latest_date":"2026-03-19 06:21:31","pct_change":44.97,"abs_change":0.76},{"id":36359,"name":"Sheba Kuipje mini filet in saus wild & konijn","supermarket":"dirk","category":"huishoud & huisdieren","unit":"85 g","unit_type":"g","price_per_unit":10,"first_price":0.59,"first_date":"2026-03-12 11:12:08","latest_price":0.85,"latest_date":"2026-03-19 06:26:55","pct_change":44.07,"abs_change":0.26},{"id":36544,"name":"Lay's Chips naturel","supermarket":"dirk","category":"snacks & snoep","unit":"175 g","unit_type":"g","price_per_unit":5.6571428571428575,"first_price":0.69,"first_date":"2026-03-12 11:12:50","latest_price":0.99,"latest_date":"2026-03-19 06:27:34","pct_change":43.48,"abs_change":0.3},{"id":36548,"name":"Lay's Chips paprika","supermarket":"dirk","category":"snacks & snoep","unit":"175 g","unit_type":"g","price_per_unit":5.6571428571428575,"first_price":0.69,"first_date":"2026-03-12 11:12:50","latest_price":0.99,"latest_date":"2026-03-19 06:27:34","pct_change":43.48,"abs_change":0.3},{"id":36713,"name":"Tony's Chocolonely wit framboos knettsersuiker","supermarket":"dirk","category":"snacks & snoep","unit":"180 g","unit_type":"g","price_per_unit":23.833333333333336,"first_price":2.99,"first_date":"2026-03-12 11:13:04","latest_price":4.29,"latest_date":"2026-03-19 06:27:48","pct_change":43.48,"abs_change":1.3},{"id":35304,"name":"Campina Botergoud grasboter ongezouten wikkel","supermarket":"dirk","category":"zuivel & kaas","unit":"250 g","unit_type":"g","price_per_unit":14.2,"first_price":2.49,"first_date":"2026-03-12 11:08:00","latest_price":3.55,"latest_date":"2026-03-19 06:22:58","pct_change":42.57,"abs_change":1.06},{"id":36357,"name":"Sheba Kuipje mini filet in saus kip & kalkoen","supermarket":"dirk","category":"huishoud & huisdieren","unit":"85 g","unit_type":"g","price_per_unit":9.882352941176471,"first_price":0.59,"first_date":"2026-03-12 11:12:08","latest_price":0.84,"latest_date":"2026-03-19 06:26:55","pct_change":42.37,"abs_change":0.25},{"id":36611,"name":"Cheetos Crunchetos flamin hot","supermarket":"dirk","category":"snacks & snoep","unit":"110 g","unit_type":"g","price_per_unit":19,"first_price":1.49,"first_date":"2026-03-12 11:12:50","latest_price":2.09,"latest_date":"2026-03-19 06:27:35","pct_change":40.27,"abs_change":0.6},{"id":36671,"name":"Tony's Chocolonely melk","supermarket":"dirk","category":"snacks & snoep","unit":"180 g","unit_type":"g","price_per_unit":23.27777777777778,"first_price":2.99,"first_date":"2026-03-12 11:13:04","latest_price":4.19,"latest_date":"2026-03-19 06:27:48","pct_change":40.13,"abs_change":1.2},{"id":36672,"name":"Tony's Chocolonely melk karamel zeezout","supermarket":"dirk","category":"snacks & snoep","unit":"180 g","unit_type":"g","price_per_unit":23.27777777777778,"first_price":2.99,"first_date":"2026-03-12 11:13:04","latest_price":4.19,"latest_date":"2026-03-19 06:27:48","pct_change":40.13,"abs_change":1.2},{"id":36685,"name":"Tony's Chocolonely melk hazelnoot","supermarket":"dirk","category":"snacks & snoep","unit":"180 g","unit_type":"g","price_per_unit":23.27777777777778,"first_price":2.99,"first_date":"2026-03-12 11:13:04","latest_price":4.19,"latest_date":"2026-03-19 06:27:48","pct_change":40.13,"abs_change":1.2},{"id":36754,"name":"Tony's Chocolonely puur","supermarket":"dirk","category":"snacks & snoep","unit":"180 g","unit_type":"g","price_per_unit":23.27777777777778,"first_price":2.99,"first_date":"2026-03-12 11:13:04","latest_price":4.19,"latest_date":"2026-03-19 06:27:49","pct_change":40.13,"abs_change":1.2},{"id":35968,"name":"1 de Beste Hummus naturel","supermarket":"dirk","category":"maaltijden, salades & tapas","unit":"200 g","unit_type":"g","price_per_unit":6.8999999999999995,"first_price":0.99,"first_date":"2026-03-12 11:10:22","latest_price":1.38,"latest_date":"2026-03-19 06:25:14","pct_change":39.39,"abs_change":0.39},{"id":35969,"name":"1 de Beste Hummus pikant","supermarket":"dirk","category":"maaltijden, salades & tapas","unit":"200 g","unit_type":"g","price_per_unit":6.8999999999999995,"first_price":0.99,"first_date":"2026-03-12 11:10:22","latest_price":1.38,"latest_date":"2026-03-19 06:25:14","pct_change":39.39,"abs_change":0.39},{"id":35090,"name":"Ouwehand Rolmops","supermarket":"dirk","category":"vlees & vis","unit":"355 g","unit_type":"g","price_per_unit":8.985915492957746,"first_price":2.29,"first_date":"2026-03-12 11:06:18","latest_price":3.19,"latest_date":"2026-03-19 06:21:24","pct_change":39.3,"abs_change":0.9},{"id":34836,"name":"Bonduelle Rode kidneybonen","supermarket":"dirk","category":"aardappelen, groente & fruit","unit":"310 g","unit_type":"g","price_per_unit":5.774193548387096,"first_price":1.29,"first_date":"2026-03-12 11:05:19","latest_price":1.79,"latest_date":"2026-03-19 06:20:44","pct_change":38.76,"abs_change":0.5},{"id":35091,"name":"Ouwehand Zure haring","supermarket":"dirk","category":"vlees & vis","unit":"355 g","unit_type":"g","price_per_unit":8.873239436619718,"first_price":2.29,"first_date":"2026-03-12 11:06:18","latest_price":3.15,"latest_date":"2026-03-19 06:21:24","pct_change":37.55,"abs_change":0.86},{"id":35261,"name":"Alpro Lekker gezond smeren soya","supermarket":"dirk","category":"zuivel & kaas","unit":"250 g","unit_type":"g","price_per_unit":6.52,"first_price":1.19,"first_date":"2026-03-12 11:08:00","latest_price":1.63,"latest_date":"2026-03-19 06:22:58","pct_change":36.97,"abs_change":0.44},{"id":19796,"name":"Jumbo Druiven Rood/Blauw Pitloos 500 g","supermarket":"jumbo","category":"aardappelen, groente & fruit","unit":"500 G","unit_type":"g","price_per_unit":5.38,"first_price":1.99,"first_date":"2026-03-12 09:05:21","latest_price":2.69,"latest_date":"2026-03-19 06:01:54","pct_change":35.18,"abs_change":0.7},{"id":34867,"name":"1 de Beste Witte bonen","supermarket":"dirk","category":"aardappelen, groente & fruit","unit":"660 g","unit_type":"g","price_per_unit":2.409090909090909,"first_price":1.19,"first_date":"2026-03-12 11:05:19","latest_price":1.59,"latest_date":"2026-03-19 06:20:44","pct_change":33.61,"abs_change":0.4},{"id":35205,"name":"Batard wit","supermarket":"dirk","category":"brood, beleg & koek","unit":"Per stuk","unit_type":"stuk","price_per_unit":1.99,"first_price":1.49,"first_date":"2026-03-12 11:06:48","latest_price":1.99,"latest_date":"2026-03-19 06:21:52","pct_change":33.56,"abs_change":0.5},{"id":35219,"name":"Batard volkoren","supermarket":"dirk","category":"brood, beleg & koek","unit":"Per stuk","unit_type":"stuk","price_per_unit":1.99,"first_price":1.49,"first_date":"2026-03-12 11:06:48","latest_price":1.99,"latest_date":"2026-03-19 06:21:52","pct_change":33.56,"abs_change":0.5},{"id":35220,"name":"Batard pompadour","supermarket":"dirk","category":"brood, beleg & koek","unit":"Per stuk","unit_type":"stuk","price_per_unit":1.99,"first_price":1.49,"first_date":"2026-03-12 11:06:48","latest_price":1.99,"latest_date":"2026-03-19 06:21:52","pct_change":33.56,"abs_change":0.5},{"id":30106,"name":"Heineken Premium Pilsener Bier Blik 6 x 500ml","supermarket":"jumbo","category":"bier & wijn","unit":"Gesponsord • 6 x 500 ml","unit_type":"ml","price_per_unit":3.0966666666666662,"first_price":6.96,"first_date":"2026-03-12 09:36:29","latest_price":9.29,"latest_date":"2026-03-19 06:15:08","pct_change":33.48,"abs_change":2.33},{"id":29941,"name":"Hertog Jan Grand Prestige Bier Flessen 6 x 30 cl","supermarket":"jumbo","category":"bier & wijn","unit":"6 x 30 CL","unit_type":"ml","price_per_unit":5.916666666666667,"first_price":7.98,"first_date":"2026-03-12 09:36:01","latest_price":10.65,"latest_date":"2026-03-19 06:15:09","pct_change":33.46,"abs_change":2.67},{"id":35085,"name":"Wokgarnalen knoflook groot","supermarket":"dirk","category":"vlees & vis","unit":"150 g","unit_type":"g","price_per_unit":26.6,"first_price":2.99,"first_date":"2026-03-12 11:06:18","latest_price":3.99,"latest_date":"2026-03-19 06:21:24","pct_change":33.44,"abs_change":1},{"id":35602,"name":"Broadleaf Merlot","supermarket":"dirk","category":"dranken, sap, koffie & thee","unit":"750 ml","unit_type":"ml","price_per_unit":5.32,"first_price":2.99,"first_date":"2026-03-12 11:09:01","latest_price":3.99,"latest_date":"2026-03-19 06:23:54","pct_change":33.44,"abs_change":1},{"id":35603,"name":"Broadleaf Shiraz cabernet sauvignon","supermarket":"dirk","category":"dranken, sap, koffie & thee","unit":"750 ml","unit_type":"ml","price_per_unit":5.32,"first_price":2.99,"first_date":"2026-03-12 11:09:01","latest_price":3.99,"latest_date":"2026-03-19 06:23:54","pct_change":33.44,"abs_change":1},{"id":35685,"name":"Broadleaf Pinot grigio","supermarket":"dirk","category":"dranken, sap, koffie & thee","unit":"750 ml","unit_type":"ml","price_per_unit":5.32,"first_price":2.99,"first_date":"2026-03-12 11:09:01","latest_price":3.99,"latest_date":"2026-03-19 06:23:54","pct_change":33.44,"abs_change":1},{"id":35724,"name":"Broadleaf Riesling","supermarket":"dirk","category":"dranken, sap, koffie & thee","unit":"75 ml","unit_type":"ml","price_per_unit":53.2,"first_price":2.99,"first_date":"2026-03-12 11:09:01","latest_price":3.99,"latest_date":"2026-03-19 06:23:54","pct_change":33.44,"abs_change":1},{"id":35730,"name":"Broadleaf Chardonnay","supermarket":"dirk","category":"dranken, sap, koffie & thee","unit":"750 ml","unit_type":"ml","price_per_unit":5.32,"first_price":2.99,"first_date":"2026-03-12 11:09:01","latest_price":3.99,"latest_date":"2026-03-19 06:23:54","pct_change":33.44,"abs_change":1},{"id":35442,"name":"Amstel Pilsener 6x33 cl","supermarket":"dirk","category":"dranken, sap, koffie & thee","unit":"1,98 liter","unit_type":"ml","price_per_unit":2.6212121212121215,"first_price":3.89,"first_date":"2026-03-12 11:08:51","latest_price":5.19,"latest_date":"2026-03-19 06:23:46","pct_change":33.42,"abs_change":1.3},{"id":35512,"name":"Hertog Jan Weizener","supermarket":"dirk","category":"dranken, sap, koffie & thee","unit":"6 x 300 ml","unit_type":"ml","price_per_unit":3.9944444444444445,"first_price":5.39,"first_date":"2026-03-12 11:08:51","latest_price":7.19,"latest_date":"2026-03-19 06:23:46","pct_change":33.4,"abs_change":1.8},{"id":35477,"name":"Hertog Jan Grand prestige","supermarket":"dirk","category":"dranken, sap, koffie & thee","unit":"6 x 300 ml","unit_type":"ml","price_per_unit":5.216666666666667,"first_price":7.04,"first_date":"2026-03-12 11:08:51","latest_price":9.39,"latest_date":"2026-03-19 06:23:46","pct_change":33.38,"abs_change":2.35},{"id":35502,"name":"Affligem Tripel 6x30cl","supermarket":"dirk","category":"dranken, sap, koffie & thee","unit":"1,8 liter","unit_type":"ml","price_per_unit":4.883333333333333,"first_price":6.59,"first_date":"2026-03-12 11:08:51","latest_price":8.79,"latest_date":"2026-03-19 06:23:46","pct_change":33.38,"abs_change":2.2},{"id":35492,"name":"Affligem Blond","supermarket":"dirk","category":"dranken, sap, koffie & thee","unit":"6 x 300 ml","unit_type":"ml","price_per_unit":4.383333333333333,"first_price":5.92,"first_date":"2026-03-12 11:08:51","latest_price":7.89,"latest_date":"2026-03-19 06:23:46","pct_change":33.28,"abs_change":1.97},{"id":35598,"name":"Gallo Family merlot","supermarket":"dirk","category":"dranken, sap, koffie & thee","unit":"750 ml","unit_type":"ml","price_per_unit":8.866666666666667,"first_price":4.99,"first_date":"2026-03-12 11:09:01","latest_price":6.65,"latest_date":"2026-03-19 06:23:54","pct_change":33.27,"abs_change":1.66},{"id":35648,"name":"Gallo Family grenache rose","supermarket":"dirk","category":"dranken, sap, koffie & thee","unit":"750 ml","unit_type":"ml","price_per_unit":8.866666666666667,"first_price":4.99,"first_date":"2026-03-12 11:09:01","latest_price":6.65,"latest_date":"2026-03-19 06:23:54","pct_change":33.27,"abs_change":1.66},{"id":35677,"name":"Gallo Family sauvignon blanc","supermarket":"dirk","category":"dranken, sap, koffie & thee","unit":"750 ml","unit_type":"ml","price_per_unit":8.866666666666667,"first_price":4.99,"first_date":"2026-03-12 11:09:01","latest_price":6.65,"latest_date":"2026-03-19 06:23:54","pct_change":33.27,"abs_change":1.66},{"id":35678,"name":"Gallo Family moscato","supermarket":"dirk","category":"dranken, sap, koffie & thee","unit":"750 ml","unit_type":"ml","price_per_unit":8.866666666666667,"first_price":4.99,"first_date":"2026-03-12 11:09:01","latest_price":6.65,"latest_date":"2026-03-19 06:23:54","pct_change":33.27,"abs_change":1.66},{"id":35447,"name":"Grolsch Pilsener 6x33 cl","supermarket":"dirk","category":"dranken, sap, koffie & thee","unit":"1,98 liter","unit_type":"ml","price_per_unit":2.8989898989898992,"first_price":4.31,"first_date":"2026-03-12 11:08:51","latest_price":5.74,"latest_date":"2026-03-19 06:23:46","pct_change":33.18,"abs_change":1.43},{"id":35460,"name":"Heineken Pilsener","supermarket":"dirk","category":"dranken, sap, koffie & thee","unit":"500 ml","unit_type":"ml","price_per_unit":2.7,"first_price":1.02,"first_date":"2026-03-12 11:08:51","latest_price":1.35,"latest_date":"2026-03-19 06:23:46","pct_change":32.35,"abs_change":0.33},{"id":35161,"name":"De Vegetarische Slager Braadworst","supermarket":"dirk","category":"vlees & vis","unit":"160 g","unit_type":"g","price_per_unit":15.562500000000002,"first_price":1.89,"first_date":"2026-03-12 11:06:26","latest_price":2.49,"latest_date":"2026-03-19 06:21:31","pct_change":31.75,"abs_change":0.6},{"id":35250,"name":"Becel Koken bakken & braden vloeibaar","supermarket":"dirk","category":"zuivel & kaas","unit":"750 ml","unit_type":"ml","price_per_unit":5.586666666666667,"first_price":3.19,"first_date":"2026-03-12 11:08:00","latest_price":4.19,"latest_date":"2026-03-19 06:22:58","pct_change":31.35,"abs_change":1},{"id":36598,"name":"Cheetos Crunchetos sweet chili","supermarket":"dirk","category":"snacks & snoep","unit":"110 g","unit_type":"g","price_per_unit":17.727272727272727,"first_price":1.49,"first_date":"2026-03-12 11:12:50","latest_price":1.95,"latest_date":"2026-03-19 06:27:34","pct_change":30.87,"abs_change":0.46},{"id":34533,"name":"Poldergoud Geschilde aardappeltjes Kruimig ongekookt","supermarket":"dirk","category":"aardappelen, groente & fruit","unit":"1 kg","unit_type":"g","price_per_unit":1.29,"first_price":0.99,"first_date":"2026-03-12 10:55:59","latest_price":1.29,"latest_date":"2026-03-19 06:20:01","pct_change":30.3,"abs_change":0.3},{"id":36564,"name":"Cheetos Nibb-it rings","supermarket":"dirk","category":"snacks & snoep","unit":"110 g","unit_type":"g","price_per_unit":17.363636363636363,"first_price":1.49,"first_date":"2026-03-12 11:12:50","latest_price":1.91,"latest_date":"2026-03-19 06:27:34","pct_change":28.19,"abs_change":0.42},{"id":36566,"name":"Cheetos Nibb-it sticks","supermarket":"dirk","category":"snacks & snoep","unit":"110 g","unit_type":"g","price_per_unit":17.363636363636363,"first_price":1.49,"first_date":"2026-03-12 11:12:50","latest_price":1.91,"latest_date":"2026-03-19 06:27:34","pct_change":28.19,"abs_change":0.42},{"id":36539,"name":"Lay's Hamka's","supermarket":"dirk","category":"snacks & snoep","unit":"125 g","unit_type":"g","price_per_unit":14.64,"first_price":1.49,"first_date":"2026-03-12 11:12:50","latest_price":1.83,"latest_date":"2026-03-19 06:27:34","pct_change":22.82,"abs_change":0.34},{"id":34740,"name":"1 de Beste Macaroni spaghetti groente","supermarket":"dirk","category":"aardappelen, groente & fruit","unit":"450 g","unit_type":"g","price_per_unit":3.7555555555555555,"first_price":1.39,"first_date":"2026-03-12 11:05:10","latest_price":1.69,"latest_date":"2026-03-19 06:20:37","pct_change":21.58,"abs_change":0.3},{"id":35784,"name":"Silvo Patatkruiden","supermarket":"dirk","category":"voorraadkast","unit":"150 g","unit_type":"g","price_per_unit":23.26666666666667,"first_price":2.89,"first_date":"2026-03-12 11:09:41","latest_price":3.49,"latest_date":"2026-03-19 06:24:33","pct_change":20.76,"abs_change":0.6},{"id":36478,"name":"Garnier Shampoo argan- & camelia olie","supermarket":"dirk","category":"kind & drogisterij","unit":"250 ml","unit_type":"ml","price_per_unit":13.96,"first_price":2.89,"first_date":"2026-03-12 11:12:29","latest_price":3.49,"latest_date":"2026-03-19 06:27:15","pct_change":20.76,"abs_change":0.6},{"id":36480,"name":"Garnier Cremespoeling argan- & camelia olie","supermarket":"dirk","category":"kind & drogisterij","unit":"200 ml","unit_type":"ml","price_per_unit":17.45,"first_price":2.89,"first_date":"2026-03-12 11:12:29","latest_price":3.49,"latest_date":"2026-03-19 06:27:15","pct_change":20.76,"abs_change":0.6},{"id":34730,"name":"Trostomaten los","supermarket":"dirk","category":"aardappelen, groente & fruit","unit":"1 kg (ca. 10 stuks)","unit_type":"g","price_per_unit":2.38,"first_price":1.98,"first_date":"2026-03-12 11:05:10","latest_price":2.38,"latest_date":"2026-03-19 06:20:37","pct_change":20.2,"abs_change":0.4},{"id":35007,"name":"Basilicum grote pot","supermarket":"dirk","category":"aardappelen, groente & fruit","unit":"Per stuk","unit_type":"stuk","price_per_unit":1.79,"first_price":1.49,"first_date":"2026-03-12 11:05:26","latest_price":1.79,"latest_date":"2026-03-19 06:20:52","pct_change":20.13,"abs_change":0.3},{"id":35008,"name":"Gember los","supermarket":"dirk","category":"aardappelen, groente & fruit","unit":"1 kg","unit_type":"g","price_per_unit":5.98,"first_price":4.98,"first_date":"2026-03-12 11:05:26","latest_price":5.98,"latest_date":"2026-03-19 06:20:52","pct_change":20.08,"abs_change":1},{"id":35851,"name":"1 de Beste Peper wit","supermarket":"dirk","category":"voorraadkast","unit":"60 g","unit_type":"g","price_per_unit":17.5,"first_price":0.88,"first_date":"2026-03-12 11:09:41","latest_price":1.05,"latest_date":"2026-03-19 06:24:33","pct_change":19.32,"abs_change":0.17},{"id":19805,"name":"Jumbo Tomaten 500g","supermarket":"jumbo","category":"aardappelen, groente & fruit","unit":"500 g","unit_type":"g","price_per_unit":3.78,"first_price":1.59,"first_date":"2026-03-12 09:05:21","latest_price":1.89,"latest_date":"2026-03-19 06:01:54","pct_change":18.87,"abs_change":0.3},{"id":36484,"name":"Hegron Haargel extra strong","supermarket":"dirk","category":"kind & drogisterij","unit":"1 liter","unit_type":"ml","price_per_unit":1.95,"first_price":1.65,"first_date":"2026-03-12 11:12:29","latest_price":1.95,"latest_date":"2026-03-19 06:27:15","pct_change":18.18,"abs_change":0.3},{"id":35202,"name":"Bolicious Mini appel-kaneelbollen","supermarket":"dirk","category":"brood, beleg & koek","unit":"360 g","unit_type":"g","price_per_unit":5.527777777777779,"first_price":1.69,"first_date":"2026-03-12 11:06:48","latest_price":1.99,"latest_date":"2026-03-19 06:21:52","pct_change":17.75,"abs_change":0.3},{"id":35086,"name":"Wokgarnalen naturel groot","supermarket":"dirk","category":"vlees & vis","unit":"150 g","unit_type":"g","price_per_unit":23.46666666666667,"first_price":2.99,"first_date":"2026-03-12 11:06:18","latest_price":3.52,"latest_date":"2026-03-19 06:21:24","pct_change":17.73,"abs_change":0.53},{"id":35461,"name":"Grolsch Pilsener","supermarket":"dirk","category":"dranken, sap, koffie & thee","unit":"500 ml","unit_type":"ml","price_per_unit":2.3,"first_price":0.98,"first_date":"2026-03-12 11:08:51","latest_price":1.15,"latest_date":"2026-03-19 06:23:46","pct_change":17.35,"abs_change":0.17},{"id":34591,"name":"1 de Beste Grote mandarijnen verpakt","supermarket":"dirk","category":"aardappelen, groente & fruit","unit":"1,5 kg","unit_type":"g","price_per_unit":2.326666666666667,"first_price":2.99,"first_date":"2026-03-12 11:04:45","latest_price":3.49,"latest_date":"2026-03-19 06:20:15","pct_change":16.72,"abs_change":0.5},{"id":34622,"name":"Gele meloen","supermarket":"dirk","category":"aardappelen, groente & fruit","unit":"Per stuk","unit_type":"stuk","price_per_unit":3.49,"first_price":2.99,"first_date":"2026-03-12 11:04:45","latest_price":3.49,"latest_date":"2026-03-19 06:20:15","pct_change":16.72,"abs_change":0.5},{"id":35088,"name":"Ouwehand Braadharing","supermarket":"dirk","category":"vlees & vis","unit":"355 g","unit_type":"g","price_per_unit":7.464788732394366,"first_price":2.29,"first_date":"2026-03-12 11:06:18","latest_price":2.65,"latest_date":"2026-03-19 06:21:24","pct_change":15.72,"abs_change":0.36},{"id":34783,"name":"Snijbonen","supermarket":"dirk","category":"aardappelen, groente & fruit","unit":"400 g","unit_type":"g","price_per_unit":3.725,"first_price":1.29,"first_date":"2026-03-12 11:05:10","latest_price":1.49,"latest_date":"2026-03-19 06:20:37","pct_change":15.5,"abs_change":0.2},{"id":34626,"name":"Kiwi green verpakt","supermarket":"dirk","category":"aardappelen, groente & fruit","unit":"1 kg","unit_type":"g","price_per_unit":3.9900000000000007,"first_price":3.49,"first_date":"2026-03-12 11:04:45","latest_price":3.99,"latest_date":"2026-03-19 06:20:15","pct_change":14.33,"abs_change":0.5},{"id":34697,"name":"Knoflook","supermarket":"dirk","category":"aardappelen, groente & fruit","unit":"3 Stuks","unit_type":"stuk","price_per_unit":0.5633333333333334,"first_price":1.49,"first_date":"2026-03-12 11:05:10","latest_price":1.69,"latest_date":"2026-03-19 06:20:37","pct_change":13.42,"abs_change":0.2},{"id":35093,"name":"Ouwehand Mosselen in natuurazijn","supermarket":"dirk","category":"vlees & vis","unit":"355 ml","unit_type":"ml","price_per_unit":7.295774647887323,"first_price":2.29,"first_date":"2026-03-12 11:06:18","latest_price":2.59,"latest_date":"2026-03-19 06:21:24","pct_change":13.1,"abs_change":0.3},{"id":31171,"name":"Jumbo Airfryer Frites 1 kg","supermarket":"jumbo","category":"diepvries","unit":"Diepvries • 1 kg","unit_type":"g","price_per_unit":2.25,"first_price":1.99,"first_date":"2026-03-12 09:39:31","latest_price":2.25,"latest_date":"2026-03-19 06:16:13","pct_change":13.07,"abs_change":0.26},{"id":34587,"name":"1 de Beste Limoenen","supermarket":"dirk","category":"aardappelen, groente & fruit","unit":"3 Stuks","unit_type":"stuk","price_per_unit":0.33,"first_price":0.89,"first_date":"2026-03-12 11:04:45","latest_price":0.99,"latest_date":"2026-03-19 06:20:15","pct_change":11.24,"abs_change":0.1},{"id":36184,"name":"Pink stuff Gel toilet cleaner","supermarket":"dirk","category":"huishoud & huisdieren","unit":"750 ml","unit_type":"ml","price_per_unit":2.6533333333333333,"first_price":1.79,"first_date":"2026-03-12 11:11:38","latest_price":1.99,"latest_date":"2026-03-19 06:26:27","pct_change":11.17,"abs_change":0.2},{"id":36580,"name":"Lay's Bugles nacho cheese","supermarket":"dirk","category":"snacks & snoep","unit":"160 g","unit_type":"g","price_per_unit":14.937500000000002,"first_price":2.15,"first_date":"2026-03-12 11:12:50","latest_price":2.39,"latest_date":"2026-03-19 06:27:34","pct_change":11.16,"abs_change":0.24},{"id":35556,"name":"Two chefs brewing Funky falcon","supermarket":"dirk","category":"dranken, sap, koffie & thee","unit":"330 ml","unit_type":"ml","price_per_unit":8.03030303030303,"first_price":2.39,"first_date":"2026-03-12 11:08:51","latest_price":2.65,"latest_date":"2026-03-19 06:23:46","pct_change":10.88,"abs_change":0.26},{"id":34627,"name":"Galia meloen","supermarket":"dirk","category":"aardappelen, groente & fruit","unit":"Per stuk","unit_type":"stuk","price_per_unit":2.19,"first_price":1.99,"first_date":"2026-03-12 11:04:45","latest_price":2.19,"latest_date":"2026-03-19 06:20:15","pct_change":10.05,"abs_change":0.2},{"id":35243,"name":"1 de Beste Vrije uitloop eieren wit S-M","supermarket":"dirk","category":"zuivel & kaas","unit":"15 Stuks","unit_type":"stuk","price_per_unit":0.366,"first_price":4.99,"first_date":"2026-03-12 11:07:54","latest_price":5.49,"latest_date":"2026-03-19 06:22:51","pct_change":10.02,"abs_change":0.5},{"id":36371,"name":"Whiskas Kattensnacks sticks rijk aan kip","supermarket":"dirk","category":"huishoud & huisdieren","unit":"18 g","unit_type":"g","price_per_unit":80.55555555555554,"first_price":1.32,"first_date":"2026-03-12 11:12:08","latest_price":1.45,"latest_date":"2026-03-19 06:26:55","pct_change":9.85,"abs_change":0.13},{"id":36275,"name":"Felix Kattenvoer sensations junior","supermarket":"dirk","category":"huishoud & huisdieren","unit":"1 kg","unit_type":"g","price_per_unit":3.89,"first_price":3.55,"first_date":"2026-03-12 11:12:08","latest_price":3.89,"latest_date":"2026-03-19 06:26:55","pct_change":9.58,"abs_change":0.34},{"id":36247,"name":"1 de Beste Kattenbakvulling absorberend stuifvrij","supermarket":"dirk","category":"huishoud & huisdieren","unit":"10 liter","unit_type":"ml","price_per_unit":0.34900000000000003,"first_price":3.19,"first_date":"2026-03-12 11:12:08","latest_price":3.49,"latest_date":"2026-03-19 06:26:55","pct_change":9.4,"abs_change":0.3},{"id":35371,"name":"Zonnatura Oplosthee 20 kruiden","supermarket":"dirk","category":"dranken, sap, koffie & thee","unit":"200 g","unit_type":"g","price_per_unit":11.950000000000001,"first_price":2.19,"first_date":"2026-03-12 11:08:40","latest_price":2.39,"latest_date":"2026-03-19 06:23:38","pct_change":9.13,"abs_change":0.2},{"id":36229,"name":"Pedigree Hondensnacks ranchos rund","supermarket":"dirk","category":"huishoud & huisdieren","unit":"70 g","unit_type":"g","price_per_unit":34.14285714285714,"first_price":2.19,"first_date":"2026-03-12 11:12:08","latest_price":2.39,"latest_date":"2026-03-19 06:26:55","pct_change":9.13,"abs_change":0.2},{"id":36755,"name":"1 de Beste Chocoladereep puur","supermarket":"dirk","category":"snacks & snoep","unit":"200 g","unit_type":"g","price_per_unit":10.249999999999998,"first_price":1.88,"first_date":"2026-03-12 11:13:04","latest_price":2.05,"latest_date":"2026-03-19 06:27:49","pct_change":9.04,"abs_change":0.17},{"id":35563,"name":"Kees Double haze","supermarket":"dirk","category":"dranken, sap, koffie & thee","unit":"330 ml","unit_type":"ml","price_per_unit":11.484848484848484,"first_price":3.49,"first_date":"2026-03-12 11:08:51","latest_price":3.79,"latest_date":"2026-03-19 06:23:46","pct_change":8.6,"abs_change":0.3},{"id":36033,"name":"1 de Beste Loempia ham/kip 2 st.","supermarket":"dirk","category":"diepvries","unit":"350 g","unit_type":"g","price_per_unit":5.114285714285715,"first_price":1.65,"first_date":"2026-03-12 11:10:44","latest_price":1.79,"latest_date":"2026-03-19 06:25:35","pct_change":8.48,"abs_change":0.14},{"id":19827,"name":"Jumbo Aardappelschijfjes 600 g","supermarket":"jumbo","category":"diepvries","unit":"Diepvries • 600 g","unit_type":"g","price_per_unit":2.15,"first_price":1.19,"first_date":"2026-03-12 09:05:26","latest_price":1.29,"latest_date":"2026-03-19 06:16:13","pct_change":8.4,"abs_change":0.1},{"id":35601,"name":"Santa Leila Valpolicella ripasso superiore","supermarket":"dirk","category":"dranken, sap, koffie & thee","unit":"750 ml","unit_type":"ml","price_per_unit":9.32,"first_price":6.45,"first_date":"2026-03-12 11:09:01","latest_price":6.99,"latest_date":"2026-03-19 06:23:54","pct_change":8.37,"abs_change":0.54},{"id":35052,"name":"Vleeschmeesters Speklap smokey 3 stuks","supermarket":"dirk","category":"vlees & vis","unit":"270 g","unit_type":"g","price_per_unit":14.407407407407408,"first_price":3.59,"first_date":"2026-03-12 11:05:41","latest_price":3.89,"latest_date":"2026-03-19 06:21:05","pct_change":8.36,"abs_change":0.3},{"id":35241,"name":"1 de Beste Vrije uitloop eieren wit M-L","supermarket":"dirk","category":"zuivel & kaas","unit":"10 Stuks","unit_type":"stuk","price_per_unit":0.389,"first_price":3.59,"first_date":"2026-03-12 11:07:54","latest_price":3.89,"latest_date":"2026-03-19 06:22:51","pct_change":8.36,"abs_change":0.3},{"id":36246,"name":"1 de Beste Kattenbakvulling houtkorrels","supermarket":"dirk","category":"huishoud & huisdieren","unit":"10 liter","unit_type":"ml","price_per_unit":0.649,"first_price":5.99,"first_date":"2026-03-12 11:12:08","latest_price":6.49,"latest_date":"2026-03-19 06:26:55","pct_change":8.35,"abs_change":0.5},{"id":20707,"name":"Iglo Roerbak Sensatie Pasta Kipfilet Boursin 450 g","supermarket":"jumbo","category":"diepvries","unit":"Gesponsord • Diepvries","unit_type":null,"price_per_unit":null,"first_price":6,"first_date":"2026-03-12 09:07:55","latest_price":6.5,"latest_date":"2026-03-19 06:16:13","pct_change":8.33,"abs_change":0.5},{"id":34870,"name":"1 de Beste Witte bonen in tomatensaus","supermarket":"dirk","category":"aardappelen, groente & fruit","unit":"700 g","unit_type":"g","price_per_unit":0.9571428571428573,"first_price":0.62,"first_date":"2026-03-12 11:05:19","latest_price":0.67,"latest_date":"2026-03-19 06:20:44","pct_change":8.06,"abs_change":0.05},{"id":36560,"name":"1 de Beste Salvos paprika","supermarket":"dirk","category":"snacks & snoep","unit":"150 g","unit_type":"g","price_per_unit":9.666666666666668,"first_price":1.35,"first_date":"2026-03-12 11:12:50","latest_price":1.45,"latest_date":"2026-03-19 06:27:34","pct_change":7.41,"abs_change":0.1},{"id":36204,"name":"1 de Beste Hondenvoer premium brokken gevogelte","supermarket":"dirk","category":"huishoud & huisdieren","unit":"3 kg","unit_type":"g","price_per_unit":2.13,"first_price":5.95,"first_date":"2026-03-12 11:12:08","latest_price":6.39,"latest_date":"2026-03-19 06:26:55","pct_change":7.39,"abs_change":0.44},{"id":35242,"name":"1 de Beste Scharreleieren wit l-xl","supermarket":"dirk","category":"zuivel & kaas","unit":"10 Stuks","unit_type":"stuk","price_per_unit":0.385,"first_price":3.59,"first_date":"2026-03-12 11:07:54","latest_price":3.85,"latest_date":"2026-03-19 06:22:51","pct_change":7.24,"abs_change":0.26},{"id":35139,"name":"Alphenhain Bakcamembert en croute","supermarket":"dirk","category":"vlees & vis","unit":"200 g","unit_type":"g","price_per_unit":14.950000000000001,"first_price":2.79,"first_date":"2026-03-12 11:06:26","latest_price":2.99,"latest_date":"2026-03-19 06:21:31","pct_change":7.17,"abs_change":0.2},{"id":36736,"name":"1 de Beste Melkchocolade hazelnoot rozijn","supermarket":"dirk","category":"snacks & snoep","unit":"200 g","unit_type":"g","price_per_unit":12.25,"first_price":2.29,"first_date":"2026-03-12 11:13:04","latest_price":2.45,"latest_date":"2026-03-19 06:27:49","pct_change":6.99,"abs_change":0.16},{"id":28890,"name":"Jumbo Green Ice Tea Pure 1,5 L","supermarket":"jumbo","category":"frisdrank & sappen","unit":"1.5 L","unit_type":"ml","price_per_unit":0.9199999999999999,"first_price":1.29,"first_date":"2026-03-12 09:32:48","latest_price":1.38,"latest_date":"2026-03-19 06:14:07","pct_change":6.98,"abs_change":0.09},{"id":36191,"name":"1 de Beste Hondenvoer senior kip-rijst","supermarket":"dirk","category":"huishoud & huisdieren","unit":"3 kg","unit_type":"g","price_per_unit":2.13,"first_price":5.99,"first_date":"2026-03-12 11:12:08","latest_price":6.39,"latest_date":"2026-03-19 06:26:55","pct_change":6.68,"abs_change":0.4},{"id":34877,"name":"1 de Beste Rode kool met appel","supermarket":"dirk","category":"aardappelen, groente & fruit","unit":"680 g","unit_type":"g","price_per_unit":0.7058823529411764,"first_price":0.45,"first_date":"2026-03-12 11:05:19","latest_price":0.48,"latest_date":"2026-03-19 06:20:44","pct_change":6.67,"abs_change":0.03},{"id":36364,"name":"Catisfactions Kattensnoepjes met kaas","supermarket":"dirk","category":"huishoud & huisdieren","unit":"60 g","unit_type":"g","price_per_unit":38.16666666666667,"first_price":2.15,"first_date":"2026-03-12 11:12:08","latest_price":2.29,"latest_date":"2026-03-19 06:26:55","pct_change":6.51,"abs_change":0.14},{"id":34864,"name":"1 de Beste Doperwten zeer fijn","supermarket":"dirk","category":"aardappelen, groente & fruit","unit":"680 g","unit_type":"g","price_per_unit":1.8235294117647058,"first_price":1.17,"first_date":"2026-03-12 11:05:19","latest_price":1.24,"latest_date":"2026-03-19 06:20:44","pct_change":5.98,"abs_change":0.07},{"id":34580,"name":"1 de Beste Handperen verpakt","supermarket":"dirk","category":"aardappelen, groente & fruit","unit":"1 kg","unit_type":"g","price_per_unit":1.79,"first_price":1.69,"first_date":"2026-03-12 11:04:45","latest_price":1.79,"latest_date":"2026-03-19 06:20:15","pct_change":5.92,"abs_change":0.1},{"id":36388,"name":"Felix Kattensnacks party mix picnic","supermarket":"dirk","category":"huishoud & huisdieren","unit":"60 g","unit_type":"g","price_per_unit":29.833333333333332,"first_price":1.69,"first_date":"2026-03-12 11:12:08","latest_price":1.79,"latest_date":"2026-03-19 06:26:55","pct_change":5.92,"abs_change":0.1},{"id":35023,"name":"Vleeschmeesters Rundersoepballetjes 250 gram","supermarket":"dirk","category":"vlees & vis","unit":"250 g","unit_type":"g","price_per_unit":14.76,"first_price":3.49,"first_date":"2026-03-12 11:05:33","latest_price":3.69,"latest_date":"2026-03-19 06:20:58","pct_change":5.73,"abs_change":0.2},{"id":35422,"name":"Hertog Jan Pilsener 0.0 6x33 cl","supermarket":"dirk","category":"dranken, sap, koffie & thee","unit":"1,98 liter","unit_type":"ml","price_per_unit":2.904040404040404,"first_price":5.45,"first_date":"2026-03-12 11:08:51","latest_price":5.75,"latest_date":"2026-03-19 06:23:46","pct_change":5.5,"abs_change":0.3},{"id":35427,"name":"Hertog Jan Pilsener 0.0","supermarket":"dirk","category":"dranken, sap, koffie & thee","unit":"330 ml","unit_type":"ml","price_per_unit":2.9696969696969697,"first_price":0.93,"first_date":"2026-03-12 11:08:51","latest_price":0.98,"latest_date":"2026-03-19 06:23:46","pct_change":5.38,"abs_change":0.05},{"id":26405,"name":"Jumbo Volkoren Beschuit 13 Stuks","supermarket":"jumbo","category":"ontbijt & broodbeleg","unit":"125 g","unit_type":"g","price_per_unit":4.72,"first_price":0.56,"first_date":"2026-03-12 09:25:20","latest_price":0.59,"latest_date":"2026-03-19 06:10:58","pct_change":5.36,"abs_change":0.03},{"id":36020,"name":"Mora Kaassouffles 6 stuks","supermarket":"dirk","category":"diepvries","unit":"360 g","unit_type":"g","price_per_unit":8.749999999999998,"first_price":2.99,"first_date":"2026-03-12 11:10:44","latest_price":3.15,"latest_date":"2026-03-19 06:25:35","pct_change":5.35,"abs_change":0.16},{"id":35496,"name":"Leffe Tripel","supermarket":"dirk","category":"dranken, sap, koffie & thee","unit":"6 x 300 ml","unit_type":"ml","price_per_unit":5.55,"first_price":9.49,"first_date":"2026-03-12 11:08:51","latest_price":9.99,"latest_date":"2026-03-19 06:23:46","pct_change":5.27,"abs_change":0.5},{"id":34590,"name":"1 de Beste Citroenen verpakt","supermarket":"dirk","category":"aardappelen, groente & fruit","unit":"500 g","unit_type":"g","price_per_unit":2.5,"first_price":1.19,"first_date":"2026-03-12 11:04:45","latest_price":1.25,"latest_date":"2026-03-19 06:20:15","pct_change":5.04,"abs_change":0.06},{"id":36193,"name":"1 de Beste Hondenvoer zachte mini brokken mix gevogelte adult","supermarket":"dirk","category":"huishoud & huisdieren","unit":"1 kg","unit_type":"g","price_per_unit":2.65,"first_price":2.79,"first_date":"2026-03-12 11:12:08","latest_price":2.65,"latest_date":"2026-03-19 06:26:55","pct_change":-5.02,"abs_change":-0.14},{"id":23057,"name":"Alpro Dessert Vanille Smaak Houdbaar 525g","supermarket":"jumbo","category":"vega & plantaardig","unit":"525 g","unit_type":"g","price_per_unit":3.6,"first_price":1.99,"first_date":"2026-03-12 09:14:30","latest_price":1.89,"latest_date":"2026-03-19 06:07:46","pct_change":-5.03,"abs_change":-0.1},{"id":34686,"name":"Komkommer","supermarket":"dirk","category":"aardappelen, groente & fruit","unit":"Per stuk","unit_type":"stuk","price_per_unit":0.75,"first_price":0.79,"first_date":"2026-03-12 11:05:10","latest_price":0.75,"latest_date":"2026-03-19 06:20:37","pct_change":-5.06,"abs_change":-0.04},{"id":22925,"name":"Jumbo Halvarine 500 g","supermarket":"jumbo","category":"zuivel, eieren & boter","unit":"500 g","unit_type":"g","price_per_unit":1.12,"first_price":0.59,"first_date":"2026-03-12 09:14:09","latest_price":0.56,"latest_date":"2026-03-19 06:06:43","pct_change":-5.08,"abs_change":-0.03},{"id":22928,"name":"Jumbo Franse Kwark Mager 1 kg","supermarket":"jumbo","category":"zuivel, eieren & boter","unit":"8+ dagen houdbaar • 1 KG","unit_type":"g","price_per_unit":1.85,"first_price":1.95,"first_date":"2026-03-12 09:14:09","latest_price":1.85,"latest_date":"2026-03-19 06:06:43","pct_change":-5.13,"abs_change":-0.1},{"id":36306,"name":"1 de Beste Kattenvoer maaltijdzakjes senior in gelei 12 stuks","supermarket":"dirk","category":"huishoud & huisdieren","unit":"1,2 kg","unit_type":"g","price_per_unit":3.075,"first_price":3.89,"first_date":"2026-03-12 11:12:08","latest_price":3.69,"latest_date":"2026-03-19 06:26:55","pct_change":-5.14,"abs_change":-0.2},{"id":28887,"name":"Jumbo Sinaasappel Sap 1,5 L","supermarket":"jumbo","category":"frisdrank & sappen","unit":"1.5 L","unit_type":"ml","price_per_unit":1.1933333333333334,"first_price":1.89,"first_date":"2026-03-12 09:32:48","latest_price":1.79,"latest_date":"2026-03-19 06:14:07","pct_change":-5.29,"abs_change":-0.1},{"id":34802,"name":"1 de Beste Kappertjes","supermarket":"dirk","category":"aardappelen, groente & fruit","unit":"100 g","unit_type":"g","price_per_unit":6.6,"first_price":0.7,"first_date":"2026-03-12 11:05:19","latest_price":0.66,"latest_date":"2026-03-19 06:20:44","pct_change":-5.71,"abs_change":-0.04},{"id":34950,"name":"1 de Beste Kikkererwten","supermarket":"dirk","category":"aardappelen, groente & fruit","unit":"200 g","unit_type":"g","price_per_unit":4.2,"first_price":0.9,"first_date":"2026-03-12 11:05:19","latest_price":0.84,"latest_date":"2026-03-19 06:20:45","pct_change":-6.67,"abs_change":-0.06},{"id":23052,"name":"Alpro Sojadrink Rode Vruchten Houdbaar 1L","supermarket":"jumbo","category":"vega & plantaardig","unit":"1 L","unit_type":"ml","price_per_unit":2.79,"first_price":2.99,"first_date":"2026-03-12 09:14:30","latest_price":2.79,"latest_date":"2026-03-19 06:07:46","pct_change":-6.69,"abs_change":-0.2},{"id":34564,"name":"Bio+ shiitake","supermarket":"dirk","category":"aardappelen, groente & fruit","unit":"100 g","unit_type":"g","price_per_unit":13.899999999999999,"first_price":1.49,"first_date":"2026-03-12 10:56:05","latest_price":1.39,"latest_date":"2026-03-19 06:20:08","pct_change":-6.71,"abs_change":-0.1}],"threshold":5,"days":30}